brotz
