Metadata-Version: 1.0
Name: brotz
Version: 0.1.1
Summary: Lightweight, chiller way to compose html in python
Home-page: http://github.com/leontrolski/brotz
Author: leontrolski
Author-email: ojhrussell@gmail.com
License: GNU General Public License v3.0
Platform: UNKNOWN
